{
    "version": 1,
    "revision": 0,
    "rules": [
        {
            "primary-output": "x64\\Debug\\math.h.obj",
            "outputs": [
                "C:\\c언어\\day3_1\\day3_1\\x64\\Debug\\vc145.pdb",
                "x64\\Debug\\",
                "C:\\c언어\\day3_1\\day3_1\\x64\\Debug\\math.h.ifc"
            ],
            "provides": [
                {
                    "logical-name": "math.h",
                    "source-path": "c:\\c언어\\day3_1\\day3_1\\math.h",
                    "lookup-method": "absolute"
                }
            ],
            "requires": []
        }
    ]
}